discord/ext/rx/__init__.py
discord/ext/rx/bot.py
discord/ext/rx/utils.py
discord_ext_rx-0.1.0.dist-info/LICENSE
discord_ext_rx-0.1.0.dist-info/METADATA
discord_ext_rx-0.1.0.dist-info/WHEEL
discord_ext_rx-0.1.0.dist-info/top_level.txt
discord_ext_rx-0.1.0.dist-info/RECORD
