Metadata-Version: 2.1
Name: discord-ext-rx
Version: 0.1.0
Summary: Combine RxPy with discord.py.
Home-page: https://github.com/NCPlayz/discord-ext-rx
Author: NCPlayz
Author-email: chowdhurynadir0@outlook.com
License: MIT
Platform: UNKNOWN
Classifier: License :: OSI Approved :: MIT License
Classifier: Intended Audience :: Developers
Classifier: Natural Language :: English
Classifier: Operating System :: OS Independent
Classifier: Programming Language :: Python :: 3.8
Classifier: Programming Language :: Python :: 3.7
Classifier: Programming Language :: Python :: 3.6
Classifier: Topic :: Internet
Classifier: Topic :: Software Development :: Libraries
Classifier: Topic :: Software Development :: Libraries :: Python Modules
Classifier: Topic :: Utilities
Requires-Python: >=3.6.0
Requires-Dist: discord.py (>0.16.12)
Requires-Dist: rx
